[{"group": {"group_lat": 50.83000183105469, "join_mode": "open", "created": 1415478004578, "group_lon": 4.329999923706055, "urlname": "Brussels-Clubbing", "id": 14245392}, "created": 1399466638000, "tallies": {"maybe": 0, "yes": 1, "waitlist": 0, "no": 4}, "rsvp_id": 1263445822, "mtime": 1399466638000, "venue": {"city": "Brussels", "name": "libertine supersport", "repinned": false, "lon": 4.3567, "address_1": "Avenue Louise 32", "country": "be", "lat": 50.834511, "id": 19963272}, "response": "no", "member": {"name": "Sean", "member_id": 74758342}, "guests": 0, "member_photo": {"thumb_link": "http://photos3.meetupstatic.com/photos/member/9/b/c/thumb_228902492.jpeg", "photo_id": 228902492, "photo_link": "http://photos1.meetupstatic.com/photos/member/9/b/c/member_228902492.jpeg", "highres_link": "http://photos3.meetupstatic.com/photos/member/9/b/c/highres_228902492.jpeg"}, "event": {"event_url": "http://www.meetup.com/Brussels-Clubbing/events/181505652/", "id": "181505652", "name": "JIMMY EDGAR@libertine supersport", "time": 1399669200000}}, {"group": {"group_lat": 50.83000183105469, "join_mode": "open", "created": 1415478004578, "group_lon": 4.329999923706055, "urlname": "Brussels-Clubbing", "id": 14245392}, "created": 1399440909000, "tallies": {"maybe": 0, "yes": 1, "waitlist": 0, "no": 4}, "rsvp_id": 1263204702, "mtime": 1399440909000, "venue": {"city": "Brussels", "name": "libertine supersport", "repinned": false, "lon": 4.3567, "address_1": "Avenue Louise 32", "country": "be", "lat": 50.834511, "id": 19963272}, "response": "no", "member": {"name": "Andrei", "member_id": 144345132}, "guests": 0, "member_photo": {"thumb_link": "http://photos3.meetupstatic.com/photos/member/4/e/9/a/thumb_195860122.jpeg", "photo_id": 195860122, "photo_link": "http://photos1.meetupstatic.com/photos/member/4/e/9/a/member_195860122.jpeg"}, "event": {"event_url": "http://www.meetup.com/Brussels-Clubbing/events/181505652/", "id": "181505652", "name": "JIMMY EDGAR@libertine supersport", "time": 1399669200000}}, {"group": {"group_lat": 50.83000183105469, "join_mode": "open", "created": 1415478004578, "group_lon": 4.329999923706055, "urlname": "Brussels-Clubbing", "id": 14245392}, "created": 1399498752000, "tallies": {"maybe": 0, "yes": 1, "waitlist": 0, "no": 4}, "rsvp_id": 1264138602, "mtime": 1399498752000, "venue": {"city": "Brussels", "name": "libertine supersport", "repinned": false, "lon": 4.3567, "address_1": "Avenue Louise 32", "country": "be", "lat": 50.834511, "id": 19963272}, "response": "no", "member": {"name": "Barbara Vangeel", "member_id": 141851812}, "guests": 0, "member_photo": {"thumb_link": "http://photos2.meetupstatic.com/photos/member/8/6/4/4/thumb_195634372.jpeg", "photo_id": 195634372, "photo_link": "http://photos2.meetupstatic.com/photos/member/8/6/4/4/member_195634372.jpeg"}, "event": {"event_url": "http://www.meetup.com/Brussels-Clubbing/events/181505652/", "id": "181505652", "name": "JIMMY EDGAR@libertine supersport", "time": 1399669200000}}, {"group": {"group_lat": 50.83000183105469, "join_mode": "open", "created": 1415478004578, "group_lon": 4.329999923706055, "urlname": "Brussels-Clubbing", "id": 14245392}, "created": 1399397895000, "tallies": {"maybe": 0, "yes": 1, "waitlist": 0, "no": 4}, "rsvp_id": 1262361282, "mtime": 1399397895000, "venue": {"city": "Brussels", "name": "libertine supersport", "repinned": false, "lon": 4.3567, "address_1": "Avenue Louise 32", "country": "be", "lat": 50.834511, "id": 19963272}, "response": "yes", "member": {"name": "Venjamin Balle", "member_id": 135311722}, "guests": 0, "member_photo": {"thumb_link": "http://photos1.meetupstatic.com/photos/member/7/d/9/8/thumb_188192152.jpeg", "photo_id": 188192152, "photo_link": "http://photos1.meetupstatic.com/photos/member/7/d/9/8/member_188192152.jpeg"}, "event": {"event_url": "http://www.meetup.com/Brussels-Clubbing/events/181505652/", "id": "181505652", "name": "JIMMY EDGAR@libertine supersport", "time": 1399669200000}}, {"group": {"group_lat": 50.83000183105469, "join_mode": "open", "created": 1415478005159, "group_lon": 4.329999923706055, "urlname": "Brussels-Clubbing", "id": 14245392}, "created": 1400693573000, "tallies": {"maybe": 0, "yes": 3, "waitlist": 0, "no": 0}, "rsvp_id": 1282446562, "mtime": 1400693573000, "venue": {"city": "Brussels", "name": "Pop-Up Art Club", "repinned": false, "lon": 4.35577, "address_1": "Rue de l'Ecuyer 50", "country": "be", "lat": 50.848789, "id": 20253012}, "response": "yes", "member": {"name": "Martin D.", "member_id": 144621012}, "guests": 0, "member_photo": {"thumb_link": "http://photos1.meetupstatic.com/photos/member/2/4/4/c/thumb_194649292.jpeg", "photo_id": 194649292, "photo_link": "http://photos3.meetupstatic.com/photos/member/2/4/4/c/member_194649292.jpeg"}, "event": {"event_url": "http://www.meetup.com/Brussels-Clubbing/events/184367562/", "id": "184367562", "name": "THIS FRIDAY AT POP - UP ART CLUB\u2502 FREE ENTRANCE\u2502", "time": 1400878800000}}, {"group": {"group_lat": 50.83000183105469, "join_mode": "open", "created": 1415478005159, "group_lon": 4.329999923706055, "urlname": "Brussels-Clubbing", "id": 14245392}, "created": 1400711999000, "tallies": {"maybe": 0, "yes": 3, "waitlist": 0, "no": 0}, "rsvp_id": 1282864122, "mtime": 1400711999000, "venue": {"city": "Brussels", "name": "Pop-Up Art Club", "repinned": false, "lon": 4.35577, "address_1": "Rue de l'Ecuyer 50", "country": "be", "lat": 50.848789, "id": 20253012}, "response": "yes", "member": {"name": "Venjamin Balle", "member_id": 135311722}, "guests": 0, "member_photo": {"thumb_link": "http://photos1.meetupstatic.com/photos/member/7/d/9/8/thumb_188192152.jpeg", "photo_id": 188192152, "photo_link": "http://photos1.meetupstatic.com/photos/member/7/d/9/8/member_188192152.jpeg"}, "event": {"event_url": "http://www.meetup.com/Brussels-Clubbing/events/184367562/", "id": "184367562", "name": "THIS FRIDAY AT POP - UP ART CLUB\u2502 FREE ENTRANCE\u2502", "time": 1400878800000}}, {"group": {"group_lat": 50.83000183105469, "join_mode": "open", "created": 1415478005777, "group_lon": 4.329999923706055, "urlname": "Brussels-Clubbing", "id": 14245392}, "created": 1400848600000, "tallies": {"maybe": 0, "yes": 1, "waitlist": 0, "no": 0}, "rsvp_id": 1284909342, "mtime": 1400848600000, "response": "yes", "member": {"name": "Martin D.", "member_id": 144621012}, "guests": 0, "member_photo": {"thumb_link": "http://photos1.meetupstatic.com/photos/member/2/4/4/c/thumb_194649292.jpeg", "photo_id": 194649292, "photo_link": "http://photos3.meetupstatic.com/photos/member/2/4/4/c/member_194649292.jpeg"}, "event": {"event_url": "http://www.meetup.com/Brussels-Clubbing/events/184742482/", "id": "184742482", "name": "Etienne De Cr\u00e9cy, Aeroplane, Compuphonic DJ set", "time": 1400952600000}}, {"group": {"group_lat": 50.83000183105469, "join_mode": "open", "created": 1415478006392, "group_lon": 4.329999923706055, "urlname": "Brussels-Clubbing", "id": 14245392}, "created": 1401041580000, "tallies": {"maybe": 0, "yes": 8, "waitlist": 0, "no": 2}, "rsvp_id": 1287369012, "mtime": 1401041585000, "venue": {"city": "Brussels", "name": "Tower\u2019s Art Galeries", "repinned": false, "lon": 4.36017, "address_1": "Rue de Brabant 23A Brabantstraat. ", "country": "be", "lat": 50.857059, "id": 19905602}, "response": "yes", "member": {"name": "Michael W", "member_id": 96439452}, "guests": 1, "member_photo": {"thumb_link": "http://photos3.meetupstatic.com/photos/member/2/7/5/8/thumb_195850072.jpeg", "photo_id": 195850072, "photo_link": "http://photos3.meetupstatic.com/photos/member/2/7/5/8/member_195850072.jpeg", "highres_link": "http://photos3.meetupstatic.com/photos/member/2/7/5/8/highres_195850072.jpeg"}, "event": {"event_url": "http://www.meetup.com/Brussels-Clubbing/events/180907782/", "id": "180907782", "name": "Perc(kompakt), Qoso and other stuff", "time": 1401486300000}}, {"group": {"group_lat": 50.83000183105469, "join_mode": "open", "created": 1415478006392, "group_lon": 4.329999923706055, "urlname": "Brussels-Clubbing", "id": 14245392}, "created": 1399466619000, "tallies": {"maybe": 0, "yes": 8, "waitlist": 0, "no": 2}, "rsvp_id": 1263445602, "mtime": 1399466619000, "venue": {"city": "Brussels", "name": "Tower\u2019s Art Galeries", "repinned": false, "lon": 4.36017, "address_1": "Rue de Brabant 23A Brabantstraat. ", "country": "be", "lat": 50.857059, "id": 19905602}, "response": "no", "member": {"name": "Sean", "member_id": 74758342}, "guests": 0, "member_photo": {"thumb_link": "http://photos3.meetupstatic.com/photos/member/9/b/c/thumb_228902492.jpeg", "photo_id": 228902492, "photo_link": "http://photos1.meetupstatic.com/photos/member/9/b/c/member_228902492.jpeg", "highres_link": "http://photos3.meetupstatic.com/photos/member/9/b/c/highres_228902492.jpeg"}, "event": {"event_url": "http://www.meetup.com/Brussels-Clubbing/events/180907782/", "id": "180907782", "name": "Perc(kompakt), Qoso and other stuff", "time": 1401486300000}}, {"group": {"group_lat": 50.83000183105469, "join_mode": "open", "created": 1415478006392, "group_lon": 4.329999923706055, "urlname": "Brussels-Clubbing", "id": 14245392}, "created": 1401295963000, "tallies": {"maybe": 0, "yes": 8, "waitlist": 0, "no": 2}, "rsvp_id": 1291372652, "mtime": 1401295963000, "venue": {"city": "Brussels", "name": "Tower\u2019s Art Galeries", "repinned": false, "lon": 4.36017, "address_1": "Rue de Brabant 23A Brabantstraat. ", "country": "be", "lat": 50.857059, "id": 19905602}, "response": "yes", "member": {"name": "Alex Coumans", "member_id": 134643802}, "guests": 0, "member_photo": {"thumb_link": "http://photos4.meetupstatic.com/photos/member/1/b/8/c/thumb_180187052.jpeg", "photo_id": 180187052, "photo_link": "http://photos2.meetupstatic.com/photos/member/1/b/8/c/member_180187052.jpeg", "highres_link": "http://photos2.meetupstatic.com/photos/member/1/b/8/c/highres_180187052.jpeg"}, "event": {"event_url": "http://www.meetup.com/Brussels-Clubbing/events/180907782/", "id": "180907782", "name": "Perc(kompakt), Qoso and other stuff", "time": 1401486300000}}, {"group": {"group_lat": 50.83000183105469, "join_mode": "open", "created": 1415478006392, "group_lon": 4.329999923706055, "urlname": "Brussels-Clubbing", "id": 14245392}, "created": 1399413217000, "tallies": {"maybe": 0, "yes": 8, "waitlist": 0, "no": 2}, "rsvp_id": 1262704772, "mtime": 1399413220000, "venue": {"city": "Brussels", "name": "Tower\u2019s Art Galeries", "repinned": false, "lon": 4.36017, "address_1": "Rue de Brabant 23A Brabantstraat. ", "country": "be", "lat": 50.857059, "id": 19905602}, "response": "yes", "member": {"name": "Julien", "member_id": 122390782}, "guests": 2, "member_photo": {"thumb_link": "http://photos2.meetupstatic.com/photos/member/6/3/4/4/thumb_190525412.jpeg", "photo_id": 190525412, "photo_link": "http://photos4.meetupstatic.com/photos/member/6/3/4/4/member_190525412.jpeg", "highres_link": "http://photos4.meetupstatic.com/photos/member/6/3/4/4/highres_190525412.jpeg"}, "event": {"event_url": "http://www.meetup.com/Brussels-Clubbing/events/180907782/", "id": "180907782", "name": "Perc(kompakt), Qoso and other stuff", "time": 1401486300000}}, {"group": {"group_lat": 50.83000183105469, "join_mode": "open", "created": 1415478006392, "group_lon": 4.329999923706055, "urlname": "Brussels-Clubbing", "id": 14245392}, "created": 1401383476000, "tallies": {"maybe": 0, "yes": 8, "waitlist": 0, "no": 2}, "rsvp_id": 1292913892, "mtime": 1401383476000, "venue": {"city": "Brussels", "name": "Tower\u2019s Art Galeries", "repinned": false, "lon": 4.36017, "address_1": "Rue de Brabant 23A Brabantstraat. ", "country": "be", "lat": 50.857059, "id": 19905602}, "response": "yes", "member": {"name": "Martin D.", "member_id": 144621012}, "guests": 0, "member_photo": {"thumb_link": "http://photos1.meetupstatic.com/photos/member/2/4/4/c/thumb_194649292.jpeg", "photo_id": 194649292, "photo_link": "http://photos3.meetupstatic.com/photos/member/2/4/4/c/member_194649292.jpeg"}, "event": {"event_url": "http://www.meetup.com/Brussels-Clubbing/events/180907782/", "id": "180907782", "name": "Perc(kompakt), Qoso and other stuff", "time": 1401486300000}}, {"group": {"group_lat": 50.83000183105469, "join_mode": "open", "created": 1415478006392, "group_lon": 4.329999923706055, "urlname": "Brussels-Clubbing", "id": 14245392}, "created": 1399134044000, "tallies": {"maybe": 0, "yes": 8, "waitlist": 0, "no": 2}, "rsvp_id": 1258168042, "mtime": 1399134044000, "venue": {"city": "Brussels", "name": "Tower\u2019s Art Galeries", "repinned": false, "lon": 4.36017, "address_1": "Rue de Brabant 23A Brabantstraat. ", "country": "be", "lat": 50.857059, "id": 19905602}, "response": "yes", "member": {"name": "Venjamin Balle", "member_id": 135311722}, "guests": 0, "member_photo": {"thumb_link": "http://photos1.meetupstatic.com/photos/member/7/d/9/8/thumb_188192152.jpeg", "photo_id": 188192152, "photo_link": "http://photos1.meetupstatic.com/photos/member/7/d/9/8/member_188192152.jpeg"}, "event": {"event_url": "http://www.meetup.com/Brussels-Clubbing/events/180907782/", "id": "180907782", "name": "Perc(kompakt), Qoso and other stuff", "time": 1401486300000}}, {"group": {"group_lat": 50.83000183105469, "join_mode": "open", "created": 1415478006392, "group_lon": 4.329999923706055, "urlname": "Brussels-Clubbing", "id": 14245392}, "created": 1399440978000, "tallies": {"maybe": 0, "yes": 8, "waitlist": 0, "no": 2}, "rsvp_id": 1263205362, "mtime": 1399440978000, "venue": {"city": "Brussels", "name": "Tower\u2019s Art Galeries", "repinned": false, "lon": 4.36017, "address_1": "Rue de Brabant 23A Brabantstraat. ", "country": "be", "lat": 50.857059, "id": 19905602}, "response": "no", "member": {"name": "Andrei", "member_id": 144345132}, "guests": 0, "member_photo": {"thumb_link": "http://photos3.meetupstatic.com/photos/member/4/e/9/a/thumb_195860122.jpeg", "photo_id": 195860122, "photo_link": "http://photos1.meetupstatic.com/photos/member/4/e/9/a/member_195860122.jpeg"}, "event": {"event_url": "http://www.meetup.com/Brussels-Clubbing/events/180907782/", "id": "180907782", "name": "Perc(kompakt), Qoso and other stuff", "time": 1401486300000}}, {"group": {"group_lat": 50.83000183105469, "join_mode": "open", "created": 1415478007003, "group_lon": 4.329999923706055, "urlname": "Brussels-Clubbing", "id": 14245392}, "created": 1401625362000, "tallies": {"maybe": 0, "yes": 2, "waitlist": 0, "no": 3}, "rsvp_id": 1296428322, "mtime": 1401625362000, "venue": {"city": "Brussels", "name": "Ancienne Belgique", "repinned": false, "lon": 4.348739, "address_1": "Anspachlaan 110", "address_2": "Anspachlaan 110", "country": "be", "lat": 50.847272, "id": 1381450}, "response": "no", "member": {"name": "Poppy", "member_id": 107367642}, "guests": 0, "member_photo": {"thumb_link": "http://photos3.meetupstatic.com/photos/member/b/8/2/6/thumb_145367142.jpeg", "photo_id": 145367142, "photo_link": "http://photos3.meetupstatic.com/photos/member/b/8/2/6/member_145367142.jpeg", "highres_link": "http://photos3.meetupstatic.com/photos/member/b/8/2/6/highres_145367142.jpeg"}, "event": {"event_url": "http://www.meetup.com/Brussels-Clubbing/events/180903562/", "id": "180903562", "name": "Plaid + Fis", "time": 1401732000000}}, {"group": {"group_lat": 50.83000183105469, "join_mode": "open", "created": 1415478007003, "group_lon": 4.329999923706055, "urlname": "Brussels-Clubbing", "id": 14245392}, "created": 1399132469000, "tallies": {"maybe": 0, "yes": 2, "waitlist": 0, "no": 3}, "rsvp_id": 1258142522, "mtime": 1399132469000, "venue": {"city": "Brussels", "name": "Ancienne Belgique", "repinned": false, "lon": 4.348739, "address_1": "Anspachlaan 110", "address_2": "Anspachlaan 110", "country": "be", "lat": 50.847272, "id": 1381450}, "response": "yes", "member": {"name": "Venjamin Balle", "member_id": 135311722}, "guests": 0, "member_photo": {"thumb_link": "http://photos1.meetupstatic.com/photos/member/7/d/9/8/thumb_188192152.jpeg", "photo_id": 188192152, "photo_link": "http://photos1.meetupstatic.com/photos/member/7/d/9/8/member_188192152.jpeg"}, "event": {"event_url": "http://www.meetup.com/Brussels-Clubbing/events/180903562/", "id": "180903562", "name": "Plaid + Fis", "time": 1401732000000}}, {"group": {"group_lat": 50.83000183105469, "join_mode": "open", "created": 1415478007003, "group_lon": 4.329999923706055, "urlname": "Brussels-Clubbing", "id": 14245392}, "created": 1399400404000, "tallies": {"maybe": 0, "yes": 2, "waitlist": 0, "no": 3}, "rsvp_id": 1262419112, "mtime": 1399400404000, "venue": {"city": "Brussels", "name": "Ancienne Belgique", "repinned": false, "lon": 4.348739, "address_1": "Anspachlaan 110", "address_2": "Anspachlaan 110", "country": "be", "lat": 50.847272, "id": 1381450}, "response": "yes", "member": {"name": "Martin D.", "member_id": 144621012}, "guests": 0, "member_photo": {"thumb_link": "http://photos1.meetupstatic.com/photos/member/2/4/4/c/thumb_194649292.jpeg", "photo_id": 194649292, "photo_link": "http://photos3.meetupstatic.com/photos/member/2/4/4/c/member_194649292.jpeg"}, "event": {"event_url": "http://www.meetup.com/Brussels-Clubbing/events/180903562/", "id": "180903562", "name": "Plaid + Fis", "time": 1401732000000}}, {"group": {"group_lat": 50.83000183105469, "join_mode": "open", "created": 1415478007003, "group_lon": 4.329999923706055, "urlname": "Brussels-Clubbing", "id": 14245392}, "created": 1401291043000, "tallies": {"maybe": 0, "yes": 2, "waitlist": 0, "no": 3}, "rsvp_id": 1291258312, "mtime": 1401291043000, "venue": {"city": "Brussels", "name": "Ancienne Belgique", "repinned": false, "lon": 4.348739, "address_1": "Anspachlaan 110", "address_2": "Anspachlaan 110", "country": "be", "lat": 50.847272, "id": 1381450}, "response": "no", "member": {"name": "Julien", "member_id": 122390782}, "guests": 0, "member_photo": {"thumb_link": "http://photos2.meetupstatic.com/photos/member/6/3/4/4/thumb_190525412.jpeg", "photo_id": 190525412, "photo_link": "http://photos4.meetupstatic.com/photos/member/6/3/4/4/member_190525412.jpeg", "highres_link": "http://photos4.meetupstatic.com/photos/member/6/3/4/4/highres_190525412.jpeg"}, "event": {"event_url": "http://www.meetup.com/Brussels-Clubbing/events/180903562/", "id": "180903562", "name": "Plaid + Fis", "time": 1401732000000}}, {"group": {"group_lat": 50.83000183105469, "join_mode": "open", "created": 1415478007003, "group_lon": 4.329999923706055, "urlname": "Brussels-Clubbing", "id": 14245392}, "created": 1400139906000, "tallies": {"maybe": 0, "yes": 2, "waitlist": 0, "no": 3}, "rsvp_id": 1274101992, "mtime": 1400139906000, "venue": {"city": "Brussels", "name": "Ancienne Belgique", "repinned": false, "lon": 4.348739, "address_1": "Anspachlaan 110", "address_2": "Anspachlaan 110", "country": "be", "lat": 50.847272, "id": 1381450}, "response": "no", "member": {"name": "Andrei", "member_id": 144345132}, "guests": 0, "member_photo": {"thumb_link": "http://photos3.meetupstatic.com/photos/member/4/e/9/a/thumb_195860122.jpeg", "photo_id": 195860122, "photo_link": "http://photos1.meetupstatic.com/photos/member/4/e/9/a/member_195860122.jpeg"}, "event": {"event_url": "http://www.meetup.com/Brussels-Clubbing/events/180903562/", "id": "180903562", "name": "Plaid + Fis", "time": 1401732000000}}, {"group": {"group_lat": 50.83000183105469, "join_mode": "open", "created": 1415478007617, "group_lon": 4.329999923706055, "urlname": "Brussels-Clubbing", "id": 14245392}, "created": 1402319236000, "tallies": {"maybe": 0, "yes": 4, "waitlist": 0, "no": 0}, "rsvp_id": 1307661072, "mtime": 1402319236000, "venue": {"city": "Brussels", "name": "Place Sainte-Croix", "repinned": false, "lon": 0, "address_1": "Flagey, next to Belga", "country": "be", "lat": 0, "id": 20584662}, "response": "yes", "member": {"name": "Michael", "member_id": 98898962}, "guests": 0, "member_photo": {"thumb_link": "http://photos3.meetupstatic.com/photos/member/a/2/0/a/thumb_169601482.jpeg", "photo_id": 169601482, "photo_link": "http://photos3.meetupstatic.com/photos/member/a/2/0/a/member_169601482.jpeg", "highres_link": "http://photos3.meetupstatic.com/photos/member/a/2/0/a/highres_169601482.jpeg"}, "event": {"event_url": "http://www.meetup.com/Brussels-Clubbing/events/187903582/", "id": "187903582", "name": "The Sound Of Belgium - documentary Free open air screening", "time": 1402518600000}}, {"group": {"group_lat": 50.83000183105469, "join_mode": "open", "created": 1415478007617, "group_lon": 4.329999923706055, "urlname": "Brussels-Clubbing", "id": 14245392}, "created": 1402251169000, "tallies": {"maybe": 0, "yes": 4, "waitlist": 0, "no": 0}, "rsvp_id": 1306643642, "mtime": 1402270083000, "venue": {"city": "Brussels", "name": "Place Sainte-Croix", "repinned": false, "lon": 0, "address_1": "Flagey, next to Belga", "country": "be", "lat": 0, "id": 20584662}, "response": "yes", "member": {"name": "Martin D.", "member_id": 144621012}, "guests": 2, "member_photo": {"thumb_link": "http://photos1.meetupstatic.com/photos/member/2/4/4/c/thumb_194649292.jpeg", "photo_id": 194649292, "photo_link": "http://photos3.meetupstatic.com/photos/member/2/4/4/c/member_194649292.jpeg"}, "event": {"event_url": "http://www.meetup.com/Brussels-Clubbing/events/187903582/", "id": "187903582", "name": "The Sound Of Belgium - documentary Free open air screening", "time": 1402518600000}}, {"group": {"group_lat": 50.83000183105469, "join_mode": "open", "created": 1415478008237, "group_lon": 4.329999923706055, "urlname": "Brussels-Clubbing", "id": 14245392}, "created": 1402872815000, "tallies": {"maybe": 0, "yes": 6, "waitlist": 0, "no": 2}, "rsvp_id": 1316273432, "mtime": 1402872815000, "venue": {"city": "Brussels", "name": "Bois de la cambre", "repinned": false, "lon": 4.641502, "address_1": "...", "country": "be", "lat": 50.648964, "id": 20584802}, "response": "no", "member": {"name": "PG (BGMonkeys)", "member_id": 90907182}, "guests": 0, "member_photo": {"thumb_link": "http://photos2.meetupstatic.com/photos/member/2/a/a/0/thumb_130990912.jpeg", "photo_id": 130990912, "photo_link": "http://photos2.meetupstatic.com/photos/member/2/a/a/0/member_130990912.jpeg", "highres_link": "http://photos2.meetupstatic.com/photos/member/2/a/a/0/highres_130990912.jpeg"}, "event": {"event_url": "http://www.meetup.com/Brussels-Clubbing/events/187905602/", "id": "187905602", "name": "Piknik Electronik", "time": 1403438400000}}, {"group": {"group_lat": 50.83000183105469, "join_mode": "open", "created": 1415478008237, "group_lon": 4.329999923706055, "urlname": "Brussels-Clubbing", "id": 14245392}, "created": 1402251668000, "tallies": {"maybe": 0, "yes": 6, "waitlist": 0, "no": 2}, "rsvp_id": 1306652492, "mtime": 1402251668000, "venue": {"city": "Brussels", "name": "Bois de la cambre", "repinned": false, "lon": 4.641502, "address_1": "...", "country": "be", "lat": 50.648964, "id": 20584802}, "response": "yes", "member": {"name": "Martin D.", "member_id": 144621012}, "guests": 0, "member_photo": {"thumb_link": "http://photos1.meetupstatic.com/photos/member/2/4/4/c/thumb_194649292.jpeg", "photo_id": 194649292, "photo_link": "http://photos3.meetupstatic.com/photos/member/2/4/4/c/member_194649292.jpeg"}, "event": {"event_url": "http://www.meetup.com/Brussels-Clubbing/events/187905602/", "id": "187905602", "name": "Piknik Electronik", "time": 1403438400000}}, {"group": {"group_lat": 50.83000183105469, "join_mode": "open", "created": 1415478008237, "group_lon": 4.329999923706055, "urlname": "Brussels-Clubbing", "id": 14245392}, "created": 1402505057000, "tallies": {"maybe": 0, "yes": 6, "waitlist": 0, "no": 2}, "rsvp_id": 1310964312, "mtime": 1402505057000, "venue": {"city": "Brussels", "name": "Bois de la cambre", "repinned": false, "lon": 4.641502, "address_1": "...", "country": "be", "lat": 50.648964, "id": 20584802}, "response": "no", "member": {"name": "Andrei", "member_id": 144345132}, "guests": 0, "member_photo": {"thumb_link": "http://photos3.meetupstatic.com/photos/member/4/e/9/a/thumb_195860122.jpeg", "photo_id": 195860122, "photo_link": "http://photos1.meetupstatic.com/photos/member/4/e/9/a/member_195860122.jpeg"}, "event": {"event_url": "http://www.meetup.com/Brussels-Clubbing/events/187905602/", "id": "187905602", "name": "Piknik Electronik", "time": 1403438400000}}, {"group": {"group_lat": 50.83000183105469, "join_mode": "open", "created": 1415478008237, "group_lon": 4.329999923706055, "urlname": "Brussels-Clubbing", "id": 14245392}, "created": 1402315919000, "tallies": {"maybe": 0, "yes": 6, "waitlist": 0, "no": 2}, "rsvp_id": 1307598182, "mtime": 1402315919000, "venue": {"city": "Brussels", "name": "Bois de la cambre", "repinned": false, "lon": 4.641502, "address_1": "...", "country": "be", "lat": 50.648964, "id": 20584802}, "response": "yes", "member": {"name": "Michael", "member_id": 98898962}, "guests": 0, "member_photo": {"thumb_link": "http://photos3.meetupstatic.com/photos/member/a/2/0/a/thumb_169601482.jpeg", "photo_id": 169601482, "photo_link": "http://photos3.meetupstatic.com/photos/member/a/2/0/a/member_169601482.jpeg", "highres_link": "http://photos3.meetupstatic.com/photos/member/a/2/0/a/highres_169601482.jpeg"}, "event": {"event_url": "http://www.meetup.com/Brussels-Clubbing/events/187905602/", "id": "187905602", "name": "Piknik Electronik", "time": 1403438400000}}, {"group": {"group_lat": 50.83000183105469, "join_mode": "open", "created": 1415478008237, "group_lon": 4.329999923706055, "urlname": "Brussels-Clubbing", "id": 14245392}, "created": 1402751407000, "tallies": {"maybe": 0, "yes": 6, "waitlist": 0, "no": 2}, "rsvp_id": 1314735252, "mtime": 1402751407000, "venue": {"city": "Brussels", "name": "Bois de la cambre", "repinned": false, "lon": 4.641502, "address_1": "...", "country": "be", "lat": 50.648964, "id": 20584802}, "response": "yes", "member": {"name": "Sophie Z.", "member_id": 151501412}, "guests": 0, "member_photo": {"thumb_link": "http://photos2.meetupstatic.com/photos/member/b/5/9/2/thumb_204406482.jpeg", "photo_id": 204406482, "photo_link": "http://photos4.meetupstatic.com/photos/member/b/5/9/2/member_204406482.jpeg", "highres_link": "http://photos2.meetupstatic.com/photos/member/b/5/9/2/highres_204406482.jpeg"}, "event": {"event_url": "http://www.meetup.com/Brussels-Clubbing/events/187905602/", "id": "187905602", "name": "Piknik Electronik", "time": 1403438400000}}, {"group": {"group_lat": 50.83000183105469, "join_mode": "open", "created": 1415478008237, "group_lon": 4.329999923706055, "urlname": "Brussels-Clubbing", "id": 14245392}, "created": 1402557204000, "tallies": {"maybe": 0, "yes": 6, "waitlist": 0, "no": 2}, "rsvp_id": 1311950552, "mtime": 1402557204000, "venue": {"city": "Brussels", "name": "Bois de la cambre", "repinned": false, "lon": 4.641502, "address_1": "...", "country": "be", "lat": 50.648964, "id": 20584802}, "response": "yes", "member": {"name": "Andr\u00e9", "member_id": 89853162}, "guests": 0, "member_photo": {"thumb_link": "http://photos2.meetupstatic.com/photos/member/7/a/a/a/thumb_113911402.jpeg", "photo_id": 113911402, "photo_link": "http://photos4.meetupstatic.com/photos/member/7/a/a/a/member_113911402.jpeg", "highres_link": "http://photos4.meetupstatic.com/photos/member/7/a/a/a/highres_113911402.jpeg"}, "event": {"event_url": "http://www.meetup.com/Brussels-Clubbing/events/187905602/", "id": "187905602", "name": "Piknik Electronik", "time": 1403438400000}}, {"group": {"group_lat": 50.83000183105469, "join_mode": "open", "created": 1415478008856, "group_lon": 4.329999923706055, "urlname": "Brussels-Clubbing", "id": 14245392}, "created": 1411643741000, "tallies": {"maybe": 0, "yes": 11, "waitlist": 0, "no": 0}, "rsvp_id": 1457922822, "mtime": 1411643741000, "response": "yes", "member": {"name": "Layla Dickerson", "member_id": 173639212}, "guests": 0, "member_photo": {"thumb_link": "http://photos3.meetupstatic.com/photos/member/6/e/c/0/thumb_229408352.jpeg", "photo_id": 229408352, "photo_link": "http://photos3.meetupstatic.com/photos/member/6/e/c/0/member_229408352.jpeg", "highres_link": "http://photos3.meetupstatic.com/photos/member/6/e/c/0/highres_229408352.jpeg"}, "event": {"event_url": "http://www.meetup.com/Brussels-Clubbing/events/208957422/", "id": "208957422", "name": "Goa party", "time": 1411848000000}}, {"group": {"group_lat": 50.83000183105469, "join_mode": "open", "created": 1415478008856, "group_lon": 4.329999923706055, "urlname": "Brussels-Clubbing", "id": 14245392}, "created": 1411668378000, "tallies": {"maybe": 0, "yes": 11, "waitlist": 0, "no": 0}, "rsvp_id": 1458391332, "mtime": 1411668378000, "response": "yes", "member": {"name": "Homer", "member_id": 109406992}, "guests": 0, "member_photo": {"thumb_link": "http://photos1.meetupstatic.com/photos/member/d/0/4/thumb_203283332.jpeg", "photo_id": 203283332, "photo_link": "http://photos3.meetupstatic.com/photos/member/d/0/4/member_203283332.jpeg", "highres_link": "http://photos1.meetupstatic.com/photos/member/d/0/4/highres_203283332.jpeg"}, "event": {"event_url": "http://www.meetup.com/Brussels-Clubbing/events/208957422/", "id": "208957422", "name": "Goa party", "time": 1411848000000}}, {"group": {"group_lat": 50.83000183105469, "join_mode": "open", "created": 1415478008856, "group_lon": 4.329999923706055, "urlname": "Brussels-Clubbing", "id": 14245392}, "created": 1411472068000, "tallies": {"maybe": 0, "yes": 11, "waitlist": 0, "no": 0}, "rsvp_id": 1454966072, "mtime": 1411472068000, "response": "yes", "member": {"name": "Anastasia Szumik", "member_id": 156395342}, "guests": 0, "member_photo": {"thumb_link": "http://photos3.meetupstatic.com/photos/member/3/e/d/2/thumb_229996082.jpeg", "photo_id": 229996082, "photo_link": "http://photos3.meetupstatic.com/photos/member/3/e/d/2/member_229996082.jpeg", "highres_link": "http://photos3.meetupstatic.com/photos/member/3/e/d/2/highres_229996082.jpeg"}, "event": {"event_url": "http://www.meetup.com/Brussels-Clubbing/events/208957422/", "id": "208957422", "name": "Goa party", "time": 1411848000000}}, {"group": {"group_lat": 50.83000183105469, "join_mode": "open", "created": 1415478008856, "group_lon": 4.329999923706055, "urlname": "Brussels-Clubbing", "id": 14245392}, "created": 1411765915000, "tallies": {"maybe": 0, "yes": 11, "waitlist": 0, "no": 0}, "rsvp_id": 1460162622, "mtime": 1411765915000, "response": "yes", "member": {"name": "Mritunjoy", "member_id": 150508942}, "guests": 0, "member_photo": {"thumb_link": "http://photos2.meetupstatic.com/photos/member/2/d/5/c/thumb_217511612.jpeg", "photo_id": 217511612, "photo_link": "http://photos2.meetupstatic.com/photos/member/2/d/5/c/member_217511612.jpeg", "highres_link": "http://photos4.meetupstatic.com/photos/member/2/d/5/c/highres_217511612.jpeg"}, "event": {"event_url": "http://www.meetup.com/Brussels-Clubbing/events/208957422/", "id": "208957422", "name": "Goa party", "time": 1411848000000}}, {"group": {"group_lat": 50.83000183105469, "join_mode": "open", "created": 1415478008856, "group_lon": 4.329999923706055, "urlname": "Brussels-Clubbing", "id": 14245392}, "created": 1411574624000, "tallies": {"maybe": 0, "yes": 11, "waitlist": 0, "no": 0}, "rsvp_id": 1456808772, "mtime": 1411574624000, "response": "yes", "member": {"name": "Olga", "member_id": 10101877}, "guests": 0, "member_photo": {"thumb_link": "http://photos2.meetupstatic.com/photos/member/3/7/4/8/thumb_197054152.jpeg", "photo_id": 197054152, "photo_link": "http://photos4.meetupstatic.com/photos/member/3/7/4/8/member_197054152.jpeg", "highres_link": "http://photos4.meetupstatic.com/photos/member/3/7/4/8/highres_197054152.jpeg"}, "event": {"event_url": "http://www.meetup.com/Brussels-Clubbing/events/208957422/", "id": "208957422", "name": "Goa party", "time": 1411848000000}}, {"group": {"group_lat": 50.83000183105469, "join_mode": "open", "created": 1415478008856, "group_lon": 4.329999923706055, "urlname": "Brussels-Clubbing", "id": 14245392}, "created": 1411643049000, "tallies": {"maybe": 0, "yes": 11, "waitlist": 0, "no": 0}, "rsvp_id": 1457915502, "mtime": 1411643049000, "response": "yes", "member": {"name": "alessandro", "member_id": 170869622}, "guests": 0, "member_photo": {"thumb_link": "http://photos4.meetupstatic.com/photos/member/e/4/9/a/thumb_229438522.jpeg", "photo_id": 229438522, "photo_link": "http://photos2.meetupstatic.com/photos/member/e/4/9/a/member_229438522.jpeg", "highres_link": "http://photos4.meetupstatic.com/photos/member/e/4/9/a/highres_229438522.jpeg"}, "event": {"event_url": "http://www.meetup.com/Brussels-Clubbing/events/208957422/", "id": "208957422", "name": "Goa party", "time": 1411848000000}}, {"group": {"group_lat": 50.83000183105469, "join_mode": "open", "created": 1415478008856, "group_lon": 4.329999923706055, "urlname": "Brussels-Clubbing", "id": 14245392}, "created": 1411674453000, "tallies": {"maybe": 0, "yes": 11, "waitlist": 0, "no": 0}, "rsvp_id": 1458553222, "mtime": 1411674453000, "response": "yes", "member": {"name": "Sundar", "member_id": 13926124}, "guests": 0, "member_photo": {"thumb_link": "http://photos3.meetupstatic.com/photos/member/4/8/8/c/thumb_36018572.jpeg", "photo_id": 36018572, "photo_link": "http://photos1.meetupstatic.com/photos/member/4/8/8/c/member_36018572.jpeg", "highres_link": "http://photos3.meetupstatic.com/photos/member/4/8/8/c/highres_36018572.jpeg"}, "event": {"event_url": "http://www.meetup.com/Brussels-Clubbing/events/208957422/", "id": "208957422", "name": "Goa party", "time": 1411848000000}}, {"group": {"group_lat": 50.83000183105469, "join_mode": "open", "created": 1415478008856, "group_lon": 4.329999923706055, "urlname": "Brussels-Clubbing", "id": 14245392}, "created": 1411484182000, "tallies": {"maybe": 0, "yes": 11, "waitlist": 0, "no": 0}, "rsvp_id": 1455192202, "mtime": 1411484182000, "response": "yes", "member": {"name": "Shahzeb Malhi", "member_id": 121782462}, "guests": 0, "member_photo": {"thumb_link": "http://photos1.meetupstatic.com/photos/member/d/1/7/6/thumb_161333622.jpeg", "photo_id": 161333622, "photo_link": "http://photos1.meetupstatic.com/photos/member/d/1/7/6/member_161333622.jpeg"}, "event": {"event_url": "http://www.meetup.com/Brussels-Clubbing/events/208957422/", "id": "208957422", "name": "Goa party", "time": 1411848000000}}, {"group": {"group_lat": 50.83000183105469, "join_mode": "open", "created": 1415478008856, "group_lon": 4.329999923706055, "urlname": "Brussels-Clubbing", "id": 14245392}, "created": 1411462301000, "tallies": {"maybe": 0, "yes": 11, "waitlist": 0, "no": 0}, "rsvp_id": 1454868192, "mtime": 1411462301000, "response": "yes", "member": {"name": "Sean", "member_id": 74758342}, "guests": 0, "member_photo": {"thumb_link": "http://photos3.meetupstatic.com/photos/member/9/b/c/thumb_228902492.jpeg", "photo_id": 228902492, "photo_link": "http://photos1.meetupstatic.com/photos/member/9/b/c/member_228902492.jpeg", "highres_link": "http://photos3.meetupstatic.com/photos/member/9/b/c/highres_228902492.jpeg"}, "event": {"event_url": "http://www.meetup.com/Brussels-Clubbing/events/208957422/", "id": "208957422", "name": "Goa party", "time": 1411848000000}}, {"group": {"group_lat": 50.83000183105469, "join_mode": "open", "created": 1415478008856, "group_lon": 4.329999923706055, "urlname": "Brussels-Clubbing", "id": 14245392}, "created": 1411717861000, "tallies": {"maybe": 0, "yes": 11, "waitlist": 0, "no": 0}, "rsvp_id": 1459333622, "mtime": 1411717861000, "response": "yes", "member": {"name": "Michael", "member_id": 98898962}, "guests": 0, "member_photo": {"thumb_link": "http://photos3.meetupstatic.com/photos/member/a/2/0/a/thumb_169601482.jpeg", "photo_id": 169601482, "photo_link": "http://photos3.meetupstatic.com/photos/member/a/2/0/a/member_169601482.jpeg", "highres_link": "http://photos3.meetupstatic.com/photos/member/a/2/0/a/highres_169601482.jpeg"}, "event": {"event_url": "http://www.meetup.com/Brussels-Clubbing/events/208957422/", "id": "208957422", "name": "Goa party", "time": 1411848000000}}, {"group": {"group_lat": 50.83000183105469, "join_mode": "open", "created": 1415478009452, "group_lon": 4.329999923706055, "urlname": "Brussels-Clubbing", "id": 14245392}, "created": 1412328896000, "tallies": {"maybe": 0, "yes": 3, "waitlist": 0, "no": 0}, "rsvp_id": 1469774392, "mtime": 1412328896000, "venue": {"city": "Brussels", "name": "Tour et Taxi", "repinned": false, "lon": 4.3488, "address_1": "Avenue du Port 86c", "country": "be", "lat": 50.864208, "id": 18320402}, "response": "yes", "member": {"name": "Sean", "member_id": 74758342}, "guests": 0, "member_photo": {"thumb_link": "http://photos3.meetupstatic.com/photos/member/9/b/c/thumb_228902492.jpeg", "photo_id": 228902492, "photo_link": "http://photos1.meetupstatic.com/photos/member/9/b/c/member_228902492.jpeg", "highres_link": "http://photos3.meetupstatic.com/photos/member/9/b/c/highres_228902492.jpeg"}, "event": {"event_url": "http://www.meetup.com/Brussels-Clubbing/events/211155882/", "id": "211155882", "name": "Blackout - Drum & Bass Festival", "time": 1413657000000}}, {"group": {"group_lat": 50.83000183105469, "join_mode": "open", "created": 1415478009452, "group_lon": 4.329999923706055, "urlname": "Brussels-Clubbing", "id": 14245392}, "created": 1412504069000, "tallies": {"maybe": 0, "yes": 3, "waitlist": 0, "no": 0}, "rsvp_id": 1472332612, "mtime": 1412504069000, "venue": {"city": "Brussels", "name": "Tour et Taxi", "repinned": false, "lon": 4.3488, "address_1": "Avenue du Port 86c", "country": "be", "lat": 50.864208, "id": 18320402}, "response": "yes", "member": {"name": "OJ", "member_id": 160005722}, "guests": 0, "member_photo": {"thumb_link": "http://photos1.meetupstatic.com/photos/member/1/6/7/8/thumb_216305752.jpeg", "photo_id": 216305752, "photo_link": "http://photos1.meetupstatic.com/photos/member/1/6/7/8/member_216305752.jpeg", "highres_link": "http://photos1.meetupstatic.com/photos/member/1/6/7/8/highres_216305752.jpeg"}, "event": {"event_url": "http://www.meetup.com/Brussels-Clubbing/events/211155882/", "id": "211155882", "name": "Blackout - Drum & Bass Festival", "time": 1413657000000}}, {"group": {"group_lat": 50.83000183105469, "join_mode": "open", "created": 1415478009452, "group_lon": 4.329999923706055, "urlname": "Brussels-Clubbing", "id": 14245392}, "created": 1413572341000, "tallies": {"maybe": 0, "yes": 3, "waitlist": 0, "no": 0}, "rsvp_id": 1490843342, "mtime": 1413572341000, "venue": {"city": "Brussels", "name": "Tour et Taxi", "repinned": false, "lon": 4.3488, "address_1": "Avenue du Port 86c", "country": "be", "lat": 50.864208, "id": 18320402}, "response": "yes", "member": {"name": "Stavroula", "member_id": 169623162}, "guests": 0, "member_photo": {"thumb_link": "http://photos4.meetupstatic.com/photos/member/e/e/4/thumb_229803812.jpeg", "photo_id": 229803812, "photo_link": "http://photos2.meetupstatic.com/photos/member/e/e/4/member_229803812.jpeg", "highres_link": "http://photos4.meetupstatic.com/photos/member/e/e/4/highres_229803812.jpeg"}, "event": {"event_url": "http://www.meetup.com/Brussels-Clubbing/events/211155882/", "id": "211155882", "name": "Blackout - Drum & Bass Festival", "time": 1413657000000}}]