[{"status": "past", "rating": {"count": 2, "average": 5}, "utc_offset": 7200000, "event_url": "http://www.meetup.com/Social-Innovation-and-Service-Design-Meetup/events/205122042/", "group": {"who": "Members", "name": "Social Innovation and Service Design Meetup", "group_lat": 50.83000183105469, "join_mode": "open", "created": 1402467455000, "group_lon": 4.329999923706055, "urlname": "Social-Innovation-and-Service-Design-Meetup", "id": 15017402}, "description": "<p>Hello and welcome! Let's get this group started! Come out to our first Meet Up to grab a drink to meet everyone\u00a0and learn about how design can create social impact.\u00a0This Meet Up is aimed at\u00a0anyone interested in using design to tackle social problems and creating real change. During this kickoff meetup we'll talk about what everyone is working on right now (even if it's just an idea), what you need help with and what our ambitions are for this Meetup Group.\u00a0I look forward to meeting everyone and don't hesitate to bring a friend!</p> <p>Hope to see you there!\u00a0</p>", "created": 1409833075000, "venue": {"city": "Brussels", "name": "Micro Marche / Via Via Cafe", "repinned": false, "lon": 4.354727, "address_1": "9 Quai de la Houille, Saint Catherine", "country": "be", "lat": 50.846281, "id": 1417149}, "updated": 1410864369000, "visibility": "public", "how_to_find_us": "How to get there: http://www.viaviacafe.com/en/content/whowhere-0", "yes_rsvp_count": 7, "time": 1410800400000, "duration": 10800000, "waitlist_count": 0, "headcount": 0, "maybe_rsvp_count": 0, "id": "205122042", "name": "Kick-off Meetup"}, {"status": "past", "rating": {"count": 0, "average": 0}, "utc_offset": 7200000, "event_url": "http://www.meetup.com/Social-Innovation-and-Service-Design-Meetup/events/210369352/", "group": {"who": "Members", "name": "Social Innovation and Service Design Meetup", "group_lat": 50.83000183105469, "join_mode": "open", "created": 1402467455000, "group_lon": 4.329999923706055, "urlname": "Social-Innovation-and-Service-Design-Meetup", "id": 15017402}, "description": "<p>Inspired by the yearly <a href=\"http://feastongood.com/worldwide/\">Feast for Good global dinner parties</a>, we are organizing a smaller version in Brussels on the same day, Oct. 11 at 7pm but with a different format. 'Feast for Good' is a social impact conference in New York, paired with a\u00a0global dinner party that brings changemakers together to imagine a brighter future for our cities.\u00a0</p> <p>These dinner parties are happening in 40+ cities across 6 continents. The goal is to spark new ideas and collaboration that drives local entrepreneurs and social initiatives forward.\u00a0The theme this year is <b>Progression</b>: we envision a world where people are empowered to love what they do.\u00a0Guests choose a common issue and who to sit with over dinner - and instead of talking about problems, they talk about ways to support each other, collaborate, and\u00a0make our city work better.</p> <p><br/>At the end of the dinner, we'll seal the night with a commitment: one small action we can take to move our city forward.\u00a0Our potluck dinner is about connecting with each other over a simple meal and participating in a global problem solving session.\u00a0</p> <p>Hope to see you there!</p> <p><br/><b><br/></b></p> <p><b>What is a potluck?\u00a0<br/></b> A potluck is gathering of people where each person brings a dish of food to be shared among the group. This is a way to have everyone be able to attend and to\u00a0distribute the costs among the participants.</p>", "created": 1412036931000, "rsvp_limit": 8, "updated": 1413059595000, "visibility": "public", "yes_rsvp_count": 5, "time": 1413046800000, "duration": 10800000, "waitlist_count": 0, "headcount": 0, "maybe_rsvp_count": 0, "id": "210369352", "name": "Feast for Good potluck"}]